uptide/__init__.py
uptide/analysis.py
uptide/ellipse.py
uptide/fes_interpolator.py
uptide/netcdf_reader.py
uptide/tidal.py
uptide/tidal_netcdf.py
uptide/tides.py
uptide-1.2.dist-info/licenses/AUTHORS
uptide-1.2.dist-info/licenses/LICENSE
uptide-1.2.dist-info/METADATA
uptide-1.2.dist-info/WHEEL
uptide-1.2.dist-info/top_level.txt
uptide-1.2.dist-info/RECORD
