Metadata-Version: 2.4
Name: uptide
Version: 1.2
Summary: uptide is a python package for tidal calculations. It computes the tidal free surface height or velocities from the amplitudes and phases of the tidal constituents. These amplitudes and phases can be read from global tidal solutions such as TPXO  or FES2014. Some limited functionality for tidal harmonic analysis is also available.
Home-page: https://github.com/stephankramer/uptide
Author: Stephan Kramer
Author-email: s.kramer@imperial.ac.uk
Keywords: tides,tidal,harmonic analysis
Classifier: Development Status :: 4 - Beta
Classifier: Intended Audience :: Science/Research
Classifier: License :: OSI Approved :: GNU Lesser General Public License v3 (LGPLv3)
Classifier: Programming Language :: Python :: 3
Classifier: Topic :: Scientific/Engineering
License-File: LICENSE
License-File: AUTHORS
Dynamic: author
Dynamic: author-email
Dynamic: classifier
Dynamic: home-page
Dynamic: keywords
Dynamic: license-file
Dynamic: summary
